{
  "runtime": "Default",
  "defaultVariables": null,
  "documentGenerator": {
    "fromDocument": {
      "url": "apiserver-swagger.json",
      "output": null,
      "newLineBehavior": "Auto"
    }
  },
  "codeGenerators": {
    "openApiToCSharpClient": {
      "classname": "{controller}Client",
      "namespace": "Laserfiche.Api.Client.APIServer",
      "output": "src/APIServer/TokenClient.cs",
      "operationGenerationMode": "MultipleClientsFromFirstTagAndPathSegments",
      "generateClientInterfaces": true,
      "generateOptionalParameters": true,
      "useBaseUrl": false,
      "generateDataAnnotations": false
    }
  }
}